Metadata-Version: 1.0
Name: rfauth0authenticator
Version: 0.1
Summary: oauthenticator custom auth0 authentication
Home-page: UNKNOWN
Author: refactored
Author-email: info@refactored.ai
License: UNKNOWN
Platform: UNKNOWN
